darbiadev_businesscentral/__init__.py
darbiadev_businesscentral/businesscentral_services.py
darbiadev_businesscentral-0.5.0.dist-info/WHEEL
darbiadev_businesscentral-0.5.0.dist-info/METADATA
darbiadev_businesscentral-0.5.0.dist-info/license_files/LICENSE
darbiadev_businesscentral-0.5.0.dist-info/RECORD
