Metadata-Version: 2.1
Name: darbiadev-businesscentral
Version: 0.5.0
Summary: darbiadev-businesscentral
License: MIT
Author-email: Bradley Reynolds <bradley.reynolds@darbia.dev>
Requires-Python: >=3.10
Requires-Dist: requests>=2.26.0
Project-URL: documentation, https://docs.darbia.dev/darbiadev-businesscentral/
Project-URL: repository, https://github.com/darbiadev/darbiadev-businesscentral/
